matiopy/__init__.py
matiopy/transform2d/transform2d.py
matiopy/vector2d/vector2d.py
matiopy-1.0.5.dist-info/licenses/LICENSE
matiopy-1.0.5.dist-info/METADATA
matiopy-1.0.5.dist-info/WHEEL
matiopy-1.0.5.dist-info/top_level.txt
matiopy-1.0.5.dist-info/RECORD
