Metadata-Version: 2.4
Name: matiopy
Version: 1.0.5
Summary: A library for 2D transformations and vector operations
Author: frigatzero, Rodion-77
License-Expression: MIT
Project-URL: Homepage, https://github.com/FrigatZero/matiopy
Requires-Python: >=3.8
License-File: LICENSE
Requires-Dist: numpy
Dynamic: license-file
